play_python/__init__.py
play_python/providers.py
play_python-0.1.1.dist-info/DESCRIPTION.rst
play_python-0.1.1.dist-info/METADATA
play_python-0.1.1.dist-info/RECORD
play_python-0.1.1.dist-info/WHEEL
play_python-0.1.1.dist-info/entry_points.txt
play_python-0.1.1.dist-info/metadata.json
play_python-0.1.1.dist-info/top_level.txt
