Metadata-Version: 2.0
Name: play-python
Version: 0.1.1
Summary: pytest-play plugin with python expressions and assertions
Home-page: https://github.com/tierratelematics/play_python
Author: Davide Moro
Author-email: davide.moro@gmail.com
License: Apache Software License 2.0
Keywords: play_python
Platform: UNKNOWN
Classifier: Development Status :: 2 - Pre-Alpha
Classifier: Intended Audience :: Developers
Classifier: License :: OSI Approved :: Apache Software License
Classifier: Natural Language :: English
Classifier: Programming Language :: Python :: 2
Classifier: Programming Language :: Python :: 2.6
Classifier: Programming Language :: Python :: 2.7
Classifier: Programming Language :: Python :: 3
Classifier: Programming Language :: Python :: 3.3
Classifier: Programming Language :: Python :: 3.4
Classifier: Programming Language :: Python :: 3.5
Requires-Dist: pytest-play (>=1.0.0)
Requires-Dist: RestrictedPython (>=4.0.b2)
Provides-Extra: tests
Requires-Dist: pytest; extra == 'tests'
Requires-Dist: mock; extra == 'tests'
Requires-Dist: pytest-cov; extra == 'tests'
